<?xml version="1.0" encoding="UTF-8" ?><root><Latitude>-81.82030994684881</Latitude><Longitude>122.98127632613847</Longitude><Priority>2</Priority><ImageType>Low</ImageType><ImageStartTime>2023-11-18T01:21:31</ImageStartTime><ImageEndTime>2023-11-18T09:21:57</ImageEndTime><DeliveryTime>2023-11-18T13:21:57</DeliveryTime><Recurrence><Revisit>True</Revisit><NumberOfRevisits>5</NumberOfRevisits><RevisitFrequency>3</RevisitFrequency><RevisitFrequencyUnits>Days</RevisitFrequencyUnits></Recurrence></root>